charlietest/__init__.py
charlietest/example.py
charlietest-0.3.0.dist-info/METADATA
charlietest-0.3.0.dist-info/WHEEL
charlietest-0.3.0.dist-info/RECORD
