Metadata-Version: 2.4
Name: charlietest
Version: 0.3.0
Summary: A simple example package using src layout (brainTest)
Author-email: Charlie Chen <test@qq.com>
Keywords: demo,example,packaging
Classifier: License :: OSI Approved :: MIT License
Classifier: Operating System :: OS Independent
Classifier: Programming Language :: Python :: 3
Classifier: Programming Language :: Python :: 3 :: Only
Classifier: Programming Language :: Python :: 3.8
Classifier: Programming Language :: Python :: 3.9
Classifier: Programming Language :: Python :: 3.10
Classifier: Programming Language :: Python :: 3.11
Requires-Python: >=3.8
Requires-Dist: requests>=2.28
